multimodal_rag/__init__.py
multimodal_rag/graph_rag.py
multimodal_rag/multimodal_rag.py
multimodal_rag/multimodal_retrieval.py
multimodal_rag/utils.py
MultimodalGraphRetrieval-0.0.1b0.dist-info/METADATA
MultimodalGraphRetrieval-0.0.1b0.dist-info/WHEEL
MultimodalGraphRetrieval-0.0.1b0.dist-info/top_level.txt
MultimodalGraphRetrieval-0.0.1b0.dist-info/RECORD
