Metadata-Version: 2.1
Name: MultimodalGraphRetrieval
Version: 0.0.1b0
Summary: Multimodal Graph retrieval
Home-page: https://github.com/jayavibhavnk/MultimodalGraphRetrieval
Author: JVNK
Author-email: jaya11vibhav@gmail.com
Classifier: Development Status :: 3 - Alpha
Requires-Dist: langchain
Requires-Dist: sentence-transformers
Requires-Dist: langchain-community
Requires-Dist: pypdf2 ==3.0.0
Requires-Dist: pypdf
Requires-Dist: pymupdf
